MANIFEST.in
README.rst
setup.cfg
setup.py
dtool_lookup_client/__init__.py
dtool_lookup_client.egg-info/PKG-INFO
dtool_lookup_client.egg-info/SOURCES.txt
dtool_lookup_client.egg-info/dependency_links.txt
dtool_lookup_client.egg-info/entry_points.txt
dtool_lookup_client.egg-info/requires.txt
dtool_lookup_client.egg-info/top_level.txt