Metadata-Version: 1.1
Name: dtool-lookup-client
Version: 0.1.0
Summary: Dtool plugin for interacting with dtool lookup server
Home-page: https://github.com/jic-dtool/dtool-lookup-client
Author: Tjelvar Olsson
Author-email: tjelvar.olsson@jic.ac.uk
License: MIT
Download-URL: https://github.com/jic-dtool/dtool-lookup-client/tarball/0.1.0
Platform: UNKNOWN
